paddle_serving_client/__init__.py
paddle_serving_client/client.py
paddle_serving_client/convert.py
paddle_serving_client/httpclient.py
paddle_serving_client/serving_client.so
paddle_serving_client/version.py
paddle_serving_client/io/__init__.py
paddle_serving_client/io/paddle_io.py
paddle_serving_client/metric/__init__.py
paddle_serving_client/metric/acc.py
paddle_serving_client/metric/auc.py
paddle_serving_client/pipeline/__init__.py
paddle_serving_client/pipeline/analyse.py
paddle_serving_client/pipeline/channel.py
paddle_serving_client/pipeline/dag.py
paddle_serving_client/pipeline/error_catch.py
paddle_serving_client/pipeline/local_service_handler.py
paddle_serving_client/pipeline/logger.py
paddle_serving_client/pipeline/operator.py
paddle_serving_client/pipeline/pipeline_client.py
paddle_serving_client/pipeline/pipeline_server.py
paddle_serving_client/pipeline/profiler.py
paddle_serving_client/pipeline/prometheus_metrics.py
paddle_serving_client/pipeline/util.py
paddle_serving_client/pipeline/gateway/__init__.py
paddle_serving_client/pipeline/gateway/libproxy_server.so
paddle_serving_client/pipeline/proto/__init__.py
paddle_serving_client/pipeline/proto/pipeline_service_pb2.py
paddle_serving_client/pipeline/proto/pipeline_service_pb2_grpc.py
paddle_serving_client/pipeline/proto/run_codegen.py
paddle_serving_client/proto/__init__.py
paddle_serving_client/proto/general_model_config_pb2.py
paddle_serving_client/proto/general_model_service_pb2.py
paddle_serving_client/proto/general_model_service_pb2_grpc.py
paddle_serving_client/proto/sdk_configure_pb2.py
paddle_serving_client/utils/__init__.py
paddle_serving_client-0.9.0.dist-info/METADATA
paddle_serving_client-0.9.0.dist-info/WHEEL
paddle_serving_client-0.9.0.dist-info/top_level.txt
paddle_serving_client-0.9.0.dist-info/RECORD
